{
  "__comment__": "This file was automatically created by mcresources",
  "type": "tfc:random_tree",
  "config": {
    "structures": [
      "tfc:weeping_maple_large/1",
      "tfc:weeping_maple_large/2",
      "tfc:weeping_maple_large/3",
      "tfc:weeping_maple_large/4",
      "tfc:weeping_maple_large/5",
      "tfc:weeping_maple_large/6",
      "tfc:weeping_maple_large/7",
      "tfc:weeping_maple_large/8",
      "tfc:weeping_maple_large/9",
      "tfc:weeping_maple_large/10",
      "tfc:weeping_maple_large/11",
      "tfc:weeping_maple_large/12",
      "tfc:weeping_maple_large/13",
      "tfc:weeping_maple_large/14"
    ],
    "radius": 1,
    "placement": {
      "width": 1,
      "height": 0,
      "allow_submerged": false
    }
  }
}