{
  "__comment__": "This file was automatically created by mcresources",
  "type": "tfc:forest_entry",
  "config": {
    "min_rain": 390,
    "max_rain": 500,
    "min_temp": 24,
    "max_temp": 40,
    "groundcover": [
      {
        "block": "tfc:wood/twig/hevea"
      },
      {
        "block": "tfc:wood/fallen_leaves/hevea"
      }
    ],
    "normal_tree": "tfc:tree/hevea",
    "dead_tree": "tfc:tree/hevea_dead",
    "fallen_log": "tfc:wood/log/hevea",
    "bush_log": {
      "Name": "tfc:wood/wood/hevea",
      "Properties": {
        "natural": "true",
        "axis": "y"
      }
    },
    "bush_leaves": "tfc:wood/leaves/hevea",
    "old_growth_tree": "tfc:tree/hevea_large"
  }
}